[
    {
        "img":"uploads/staff/372.jpeg",
        "name":"C. Puttamallaiah",
        "degree":"",
        "designation":"Senior Technical Assistant",
        "address":"ICAR-CTRI RS, Hunsur",
        "phone":"9341282820",
        "email":"puttamalliah@gmail.com",

        "employment_record": [
              
            "Senior Technician 2001 - 2011",
            "Technical Assistant 2011 - till date."

        ],

        "area_of_interst":"",

        "publications":[ 

                
                
        ],

        "awards":[

                

        ]

        

    

      
    }
]  